{"v":"5.7.3","fr":25,"ip":0,"op":125,"w":600,"h":600,"nm":"animFeatherIcon","ddd":0,"assets":[],"layers":[{"ddd":0,"ind":1,"ty":4,"nm":"FeatherLogo","parent":3,"sr":1,"ks":{"o":{"a":0,"k":100,"ix":11},"r":{"a":0,"k":0,"ix":10},"p":{"a":0,"k":[0,4.065,0],"ix":2},"a":{"a":0,"k":[0,4.065,0],"ix":1},"s":{"a":0,"k":[100,100,100],"ix":6}},"ao":0,"shapes":[{"ty":"gr","it":[{"ind":0,"ty":"sh","ix":1,"ks":{"a":0,"k":{"i":[[-28.619,4.634],[22.043,-17.759]],"o":[[-29.223,9.221],[14.029,-17.081]],"v":[[33.43,-19.732],[-32.336,17.917]],"c":true},"ix":2},"nm":"Path 1","mn":"ADBE Vector Shape - Group","hd":false},{"ind":1,"ty":"sh","ix":2,"ks":{"a":0,"k":{"i":[[-5.308,1.161],[0.74,0.733],[-6.827,4.298],[1.127,0.275],[1.331,0.559],[-5.827,5.549],[1.034,1.051],[-4.355,2.686],[-1.508,1.162],[0.082,0.227],[2.479,0.285],[-6.823,7.887],[8.019,-1.87],[6.325,-5.178],[-0.703,1.869],[4.039,-3.996],[0.702,-1.837],[0.379,1.697],[2.808,-10.755],[-0.257,2.296],[0.903,-3.069],[0.307,1.572],[0.459,-1.551],[0.401,0.367],[0.079,-0.205],[0.1,-0.968],[4.337,-4.353],[1.261,-1.509],[-0.157,-0.172],[-1.537,1.278],[-1.523,1.417],[-3.49,0.554]],"o":[[-1.038,-1.029],[9.007,1.257],[-1.12,-0.374],[-1.216,-0.297],[8.251,0.994],[-0.388,-0.395],[7.134,1.862],[1.617,-0.997],[-0.082,-0.227],[-2.479,-0.285],[9.829,-2.344],[-9.348,-4.124],[-7.919,1.846],[0.516,-1.371],[-5.815,1.869],[-1.194,1.182],[-0.229,-1.025],[-8.134,5.598],[0.272,-2.435],[-2.64,1.861],[-0.207,-1.059],[-0.539,1.819],[-0.66,-0.603],[-0.146,0.191],[-0.346,0.896],[-0.723,6.98],[-1.378,1.383],[0.157,0.172],[1.583,-1.22],[1.597,-1.329],[2.491,-2.317],[4.903,-0.778]],"v":[[-17.634,20.207],[-19.87,17.992],[2.841,11.512],[-0.52,10.411],[-4.295,9.422],[17.165,3.649],[15.172,1.623],[29.632,-4.473],[34.174,-7.934],[33.929,-8.614],[26.492,-9.468],[51.47,-24.256],[25.926,-25.525],[4.143,-15.854],[5.879,-20.466],[-9.399,-12.895],[-11.521,-7.645],[-12.392,-11.549],[-31.418,10.037],[-30.617,2.871],[-33.632,11.447],[-34.353,7.757],[-35.742,12.447],[-37.159,11.151],[-37.565,11.696],[-38.522,14.419],[-47.67,30.246],[-51.47,34.752],[-51,35.269],[-46.26,31.596],[-41.599,27.448],[-32.607,23.408]],"c":true},"ix":2},"nm":"Path 2","mn":"ADBE Vector Shape - Group","hd":false},{"ty":"gf","o":{"a":0,"k":100,"ix":10},"r":1,"bm":0,"g":{"p":3,"k":{"a":0,"k":[0,1,0.498,0.047,0.5,0.992,0.263,0.245,1,0.984,0.027,0.443],"ix":9}},"s":{"a":0,"k":[-199.58,109.158],"ix":5},"e":{"a":0,"k":[0,0],"ix":6},"t":1,"nm":"Gradient Fill 1","mn":"ADBE Vector Graphic - G-Fill","hd":false},{"ty":"tr","p":{"a":0,"k":[0,0],"ix":2},"a":{"a":0,"k":[0,0],"ix":1},"s":{"a":0,"k":[100,100],"ix":3},"r":{"a":0,"k":0,"ix":6},"o":{"a":0,"k":100,"ix":7},"sk":{"a":0,"k":0,"ix":4},"sa":{"a":0,"k":0,"ix":5},"nm":"Transform"}],"nm":"Group 1","np":3,"cix":2,"bm":0,"ix":1,"mn":"ADBE Vector Group","hd":false}],"ip":0,"op":125,"st":0,"bm":0},{"ddd":0,"ind":2,"ty":4,"nm":"FeatherCircle","parent":3,"sr":1,"ks":{"o":{"a":0,"k":100,"ix":11},"r":{"a":0,"k":0,"ix":10},"p":{"a":0,"k":[0,0,0],"ix":2},"a":{"a":0,"k":[0,0,0],"ix":1},"s":{"a":0,"k":[100,100,100],"ix":6}},"ao":0,"shapes":[{"ty":"gr","it":[{"ind":0,"ty":"sh","ix":1,"ks":{"a":0,"k":{"i":[[0,-40.685],[40.685,0],[0,40.685],[-40.685,0]],"o":[[0,40.685],[-40.685,0],[0,-40.685],[40.685,0]],"v":[[73.667,0],[0,73.667],[-73.667,0],[0,-73.667]],"c":true},"ix":2},"nm":"Path 1","mn":"ADBE Vector Shape - Group","hd":false},{"ty":"gs","o":{"a":0,"k":100,"ix":9},"w":{"a":0,"k":4.5,"ix":10},"g":{"p":3,"k":{"a":0,"k":[0,1,0.498,0.047,0.5,0.992,0.263,0.245,1,0.984,0.027,0.443],"ix":8}},"s":{"a":0,"k":[-71,25],"ix":4},"e":{"a":0,"k":[71.714,-26.944],"ix":5},"t":1,"lc":1,"lj":1,"ml":10,"ml2":{"a":0,"k":10,"ix":13},"bm":0,"nm":"Gradient Stroke 1","mn":"ADBE Vector Graphic - G-Stroke","hd":false},{"ty":"tr","p":{"a":0,"k":[0,0],"ix":2},"a":{"a":0,"k":[0,0],"ix":1},"s":{"a":0,"k":[100,100],"ix":3},"r":{"a":0,"k":0,"ix":6},"o":{"a":0,"k":100,"ix":7},"sk":{"a":0,"k":0,"ix":4},"sa":{"a":0,"k":0,"ix":5},"nm":"Transform"}],"nm":"Group 1","np":2,"cix":2,"bm":0,"ix":1,"mn":"ADBE Vector Group","hd":false}],"ip":0,"op":125,"st":0,"bm":0},{"ddd":0,"ind":3,"ty":4,"nm":"FeatherBG","sr":1,"ks":{"o":{"a":0,"k":100,"ix":11},"r":{"a":0,"k":0,"ix":10},"p":{"a":0,"k":[300,300,0],"ix":2},"a":{"a":0,"k":[0,0,0],"ix":1},"s":{"a":0,"k":[100,100,100],"ix":6}},"ao":0,"shapes":[{"ty":"gr","it":[{"d":1,"ty":"el","s":{"a":0,"k":[181.333,181.333],"ix":2},"p":{"a":0,"k":[0,0],"ix":3},"nm":"Ellipse Path 1","mn":"ADBE Vector Shape - Ellipse","hd":false},{"ty":"gf","o":{"a":0,"k":100,"ix":10},"r":1,"bm":0,"g":{"p":5,"k":{"a":0,"k":[0,0.165,0,0,0.447,0.147,0.049,0.045,0.893,0.129,0.098,0.09,0.952,0.135,0.124,0.137,1,0.141,0.149,0.184],"ix":9}},"s":{"a":0,"k":[0,0],"ix":5},"e":{"a":0,"k":[90.667,0],"ix":6},"t":2,"h":{"a":0,"k":0,"ix":7},"a":{"a":0,"k":0,"ix":8},"nm":"Gradient Fill 1","mn":"ADBE Vector Graphic - G-Fill","hd":false},{"ty":"tr","p":{"a":0,"k":[0,0],"ix":2},"a":{"a":0,"k":[0,0],"ix":1},"s":{"a":0,"k":[100,100],"ix":3},"r":{"a":0,"k":0,"ix":6},"o":{"a":0,"k":100,"ix":7},"sk":{"a":0,"k":0,"ix":4},"sa":{"a":0,"k":0,"ix":5},"nm":"Transform"}],"nm":"Group 1","np":2,"cix":2,"bm":0,"ix":1,"mn":"ADBE Vector Group","hd":false}],"ip":0,"op":125,"st":0,"bm":0},{"ddd":0,"ind":4,"ty":4,"nm":"Circkle_9","sr":1,"ks":{"o":{"a":0,"k":20,"ix":11},"r":{"a":0,"k":0,"ix":10},"p":{"a":0,"k":[300,300,0],"ix":2},"a":{"a":0,"k":[0,0,0],"ix":1},"s":{"a":0,"k":[100,100,100],"ix":6}},"ao":0,"shapes":[{"ty":"gr","it":[{"ind":0,"ty":"sh","ix":1,"ks":{"a":0,"k":{"i":[[0,-155.858],[155.858,0],[0,155.858],[-155.858,0]],"o":[[0,155.858],[-155.858,0],[0,-155.858],[155.858,0]],"v":[[282.206,0],[0,282.206],[-282.206,0],[0,-282.206]],"c":true},"ix":2},"nm":"Path 1","mn":"ADBE Vector Shape - Group","hd":false},{"ty":"fl","c":{"a":0,"k":[0,0,0,1],"ix":4},"o":{"a":0,"k":15,"ix":5},"r":1,"bm":0,"nm":"Fill 1","mn":"ADBE Vector Graphic - Fill","hd":false},{"ty":"gs","o":{"a":0,"k":100,"ix":9},"w":{"a":0,"k":0.5,"ix":10},"g":{"p":3,"k":{"a":0,"k":[0,1,0.498,0.047,0.5,0.992,0.263,0.245,1,0.984,0.027,0.443],"ix":8}},"s":{"a":0,"k":[-265,96],"ix":4},"e":{"a":0,"k":[265.895,-97.23],"ix":5},"t":1,"lc":1,"lj":1,"ml":10,"ml2":{"a":0,"k":10,"ix":13},"bm":0,"nm":"Gradient Stroke 1","mn":"ADBE Vector Graphic - G-Stroke","hd":false},{"ty":"tr","p":{"a":0,"k":[0,0],"ix":2},"a":{"a":0,"k":[0,0],"ix":1},"s":{"a":0,"k":[100,100],"ix":3},"r":{"a":0,"k":0,"ix":6},"o":{"a":0,"k":100,"ix":7},"sk":{"a":0,"k":0,"ix":4},"sa":{"a":0,"k":0,"ix":5},"nm":"Transform"}],"nm":"Group 1","np":3,"cix":2,"bm":0,"ix":1,"mn":"ADBE Vector Group","hd":false}],"ip":0,"op":125,"st":0,"bm":0},{"ddd":0,"ind":5,"ty":4,"nm":"Circkle_8","sr":1,"ks":{"o":{"a":0,"k":30,"ix":11},"r":{"a":0,"k":0,"ix":10},"p":{"a":0,"k":[300,300,0],"ix":2},"a":{"a":0,"k":[0,0,0],"ix":1},"s":{"a":0,"k":[100,100,100],"ix":6}},"ao":0,"shapes":[{"ty":"gr","it":[{"ind":0,"ty":"sh","ix":1,"ks":{"a":0,"k":{"i":[[0,-147.72],[147.72,0],[0,147.72],[-147.72,0]],"o":[[0,147.72],[-147.72,0],[0,-147.72],[147.72,0]],"v":[[267.47,0],[0,267.47],[-267.47,0],[0,-267.47]],"c":true},"ix":2},"nm":"Path 1","mn":"ADBE Vector Shape - Group","hd":false},{"ty":"gs","o":{"a":0,"k":100,"ix":9},"w":{"a":0,"k":0.5,"ix":10},"g":{"p":3,"k":{"a":0,"k":[0,1,0.498,0.047,0.5,0.992,0.263,0.245,1,0.984,0.027,0.443],"ix":8}},"s":{"a":0,"k":[-251,91],"ix":4},"e":{"a":0,"k":[252.192,-92.147],"ix":5},"t":1,"lc":1,"lj":1,"ml":10,"ml2":{"a":0,"k":10,"ix":13},"bm":0,"nm":"Gradient Stroke 1","mn":"ADBE Vector Graphic - G-Stroke","hd":false},{"ty":"tr","p":{"a":0,"k":[0,0],"ix":2},"a":{"a":0,"k":[0,0],"ix":1},"s":{"a":0,"k":[100,100],"ix":3},"r":{"a":0,"k":0,"ix":6},"o":{"a":0,"k":100,"ix":7},"sk":{"a":0,"k":0,"ix":4},"sa":{"a":0,"k":0,"ix":5},"nm":"Transform"}],"nm":"Group 1","np":2,"cix":2,"bm":0,"ix":1,"mn":"ADBE Vector Group","hd":false}],"ip":0,"op":125,"st":0,"bm":0},{"ddd":0,"ind":6,"ty":4,"nm":"Circkle_7","sr":1,"ks":{"o":{"a":0,"k":40,"ix":11},"r":{"a":0,"k":0,"ix":10},"p":{"a":0,"k":[300,300,0],"ix":2},"a":{"a":0,"k":[0,0,0],"ix":1},"s":{"a":0,"k":[100,100,100],"ix":6}},"ao":0,"shapes":[{"ty":"gr","it":[{"ind":0,"ty":"sh","ix":1,"ks":{"a":0,"k":{"i":[[0,-139.076],[139.076,0],[0,139.076],[-139.076,0]],"o":[[0,139.076],[-139.076,0],[0,-139.076],[139.076,0]],"v":[[251.819,0],[0,251.819],[-251.819,0],[0,-251.819]],"c":true},"ix":2},"nm":"Path 1","mn":"ADBE Vector Shape - Group","hd":false},{"ty":"gs","o":{"a":0,"k":100,"ix":9},"w":{"a":0,"k":0.5,"ix":10},"g":{"p":3,"k":{"a":0,"k":[0,1,0.498,0.047,0.5,0.992,0.263,0.245,1,0.984,0.027,0.443],"ix":8}},"s":{"a":0,"k":[-236,86],"ix":4},"e":{"a":0,"k":[237.77,-86.438],"ix":5},"t":1,"lc":1,"lj":1,"ml":10,"ml2":{"a":0,"k":10,"ix":13},"bm":0,"nm":"Gradient Stroke 1","mn":"ADBE Vector Graphic - G-Stroke","hd":false},{"ty":"tr","p":{"a":0,"k":[0,0],"ix":2},"a":{"a":0,"k":[0,0],"ix":1},"s":{"a":0,"k":[100,100],"ix":3},"r":{"a":0,"k":0,"ix":6},"o":{"a":0,"k":100,"ix":7},"sk":{"a":0,"k":0,"ix":4},"sa":{"a":0,"k":0,"ix":5},"nm":"Transform"}],"nm":"Group 1","np":2,"cix":2,"bm":0,"ix":1,"mn":"ADBE Vector Group","hd":false}],"ip":0,"op":125,"st":0,"bm":0},{"ddd":0,"ind":7,"ty":4,"nm":"Circkle_6","sr":1,"ks":{"o":{"a":0,"k":50,"ix":11},"r":{"a":0,"k":0,"ix":10},"p":{"a":0,"k":[300,300,0],"ix":2},"a":{"a":0,"k":[0,0,0],"ix":1},"s":{"a":0,"k":[100,100,100],"ix":6}},"ao":0,"shapes":[{"ty":"gr","it":[{"d":1,"ty":"el","s":{"a":0,"k":[464.729,464.729],"ix":2},"p":{"a":0,"k":[0,0],"ix":3},"nm":"Ellipse Path 1","mn":"ADBE Vector Shape - Ellipse","hd":false},{"ty":"gs","o":{"a":0,"k":100,"ix":9},"w":{"a":0,"k":0.5,"ix":10},"g":{"p":3,"k":{"a":0,"k":[0,1,0.498,0.047,0.5,0.992,0.263,0.245,1,0.984,0.027,0.443],"ix":8}},"s":{"a":0,"k":[-218,79],"ix":4},"e":{"a":0,"k":[219.197,-80.127],"ix":5},"t":1,"lc":1,"lj":1,"ml":10,"ml2":{"a":0,"k":10,"ix":13},"bm":0,"nm":"Gradient Stroke 1","mn":"ADBE Vector Graphic - G-Stroke","hd":false},{"ty":"tr","p":{"a":0,"k":[0,0],"ix":2},"a":{"a":0,"k":[0,0],"ix":1},"s":{"a":0,"k":[100,100],"ix":3},"r":{"a":0,"k":0,"ix":6},"o":{"a":0,"k":100,"ix":7},"sk":{"a":0,"k":0,"ix":4},"sa":{"a":0,"k":0,"ix":5},"nm":"Transform"}],"nm":"Group 1","np":2,"cix":2,"bm":0,"ix":1,"mn":"ADBE Vector Group","hd":false}],"ip":0,"op":125,"st":0,"bm":0},{"ddd":0,"ind":8,"ty":4,"nm":"Circkle_5","sr":1,"ks":{"o":{"a":0,"k":60,"ix":11},"r":{"a":0,"k":0,"ix":10},"p":{"a":0,"k":[300,300,0],"ix":2},"a":{"a":0,"k":[0,0,0],"ix":1},"s":{"a":0,"k":[100,100,100],"ix":6}},"ao":0,"shapes":[{"ty":"gr","it":[{"d":1,"ty":"el","s":{"a":0,"k":[429.527,429.527],"ix":2},"p":{"a":0,"k":[0,0],"ix":3},"nm":"Ellipse Path 1","mn":"ADBE Vector Shape - Ellipse","hd":false},{"ty":"gs","o":{"a":0,"k":100,"ix":9},"w":{"a":0,"k":0.5,"ix":10},"g":{"p":3,"k":{"a":0,"k":[0,1,0.498,0.047,0.5,0.992,0.263,0.245,1,0.984,0.027,0.443],"ix":8}},"s":{"a":0,"k":[-202,73],"ix":4},"e":{"a":0,"k":[202.109,-74.084],"ix":5},"t":1,"lc":1,"lj":1,"ml":10,"ml2":{"a":0,"k":10,"ix":13},"bm":0,"nm":"Gradient Stroke 1","mn":"ADBE Vector Graphic - G-Stroke","hd":false},{"ty":"tr","p":{"a":0,"k":[0,0],"ix":2},"a":{"a":0,"k":[0,0],"ix":1},"s":{"a":0,"k":[100,100],"ix":3},"r":{"a":0,"k":0,"ix":6},"o":{"a":0,"k":100,"ix":7},"sk":{"a":0,"k":0,"ix":4},"sa":{"a":0,"k":0,"ix":5},"nm":"Transform"}],"nm":"Group 1","np":2,"cix":2,"bm":0,"ix":1,"mn":"ADBE Vector Group","hd":false}],"ip":0,"op":125,"st":0,"bm":0},{"ddd":0,"ind":9,"ty":4,"nm":"Circkle_4","sr":1,"ks":{"o":{"a":0,"k":70,"ix":11},"r":{"a":0,"k":0,"ix":10},"p":{"a":0,"k":[300,300,0],"ix":2},"a":{"a":0,"k":[0,0,0],"ix":1},"s":{"a":0,"k":[100,100,100],"ix":6}},"ao":0,"shapes":[{"ty":"gr","it":[{"ind":0,"ty":"sh","ix":1,"ks":{"a":0,"k":{"i":[[0,-108.43],[108.43,0],[0,108.43],[-108.43,0]],"o":[[0,108.43],[-108.43,0],[0,-108.43],[108.43,0]],"v":[[196.33,0],[0,196.33],[-196.33,0],[0,-196.33]],"c":true},"ix":2},"nm":"Path 1","mn":"ADBE Vector Shape - Group","hd":false},{"ty":"gs","o":{"a":0,"k":100,"ix":9},"w":{"a":0,"k":0.5,"ix":10},"g":{"p":3,"k":{"a":0,"k":[0,1,0.498,0.047,0.5,0.992,0.263,0.245,1,0.984,0.027,0.443],"ix":8}},"s":{"a":0,"k":[-184,67],"ix":4},"e":{"a":0,"k":[185.457,-67.471],"ix":5},"t":1,"lc":1,"lj":1,"ml":10,"ml2":{"a":0,"k":10,"ix":13},"bm":0,"nm":"Gradient Stroke 1","mn":"ADBE Vector Graphic - G-Stroke","hd":false},{"ty":"tr","p":{"a":0,"k":[0,0],"ix":2},"a":{"a":0,"k":[0,0],"ix":1},"s":{"a":0,"k":[100,100],"ix":3},"r":{"a":0,"k":0,"ix":6},"o":{"a":0,"k":100,"ix":7},"sk":{"a":0,"k":0,"ix":4},"sa":{"a":0,"k":0,"ix":5},"nm":"Transform"}],"nm":"Group 1","np":2,"cix":2,"bm":0,"ix":1,"mn":"ADBE Vector Group","hd":false}],"ip":0,"op":125,"st":0,"bm":0},{"ddd":0,"ind":10,"ty":4,"nm":"Circkle_3","sr":1,"ks":{"o":{"a":0,"k":80,"ix":11},"r":{"a":0,"k":0,"ix":10},"p":{"a":0,"k":[300,300,0],"ix":2},"a":{"a":0,"k":[0,0,0],"ix":1},"s":{"a":0,"k":[100,100,100],"ix":6}},"ao":0,"shapes":[{"ty":"gr","it":[{"d":1,"ty":"el","s":{"a":0,"k":[361.075,361.075],"ix":2},"p":{"a":0,"k":[0,0],"ix":3},"nm":"Ellipse Path 1","mn":"ADBE Vector Shape - Ellipse","hd":false},{"ty":"gs","o":{"a":0,"k":100,"ix":9},"w":{"a":0,"k":0.5,"ix":10},"g":{"p":3,"k":{"a":0,"k":[0,1,0.498,0.047,0.5,0.992,0.263,0.245,1,0.984,0.027,0.443],"ix":8}},"s":{"a":0,"k":[-169,61],"ix":4},"e":{"a":0,"k":[170.768,-62.666],"ix":5},"t":1,"lc":1,"lj":1,"ml":10,"ml2":{"a":0,"k":10,"ix":13},"bm":0,"nm":"Gradient Stroke 1","mn":"ADBE Vector Graphic - G-Stroke","hd":false},{"ty":"tr","p":{"a":0,"k":[0,0],"ix":2},"a":{"a":0,"k":[0,0],"ix":1},"s":{"a":0,"k":[100,100],"ix":3},"r":{"a":0,"k":0,"ix":6},"o":{"a":0,"k":100,"ix":7},"sk":{"a":0,"k":0,"ix":4},"sa":{"a":0,"k":0,"ix":5},"nm":"Transform"}],"nm":"Group 1","np":2,"cix":2,"bm":0,"ix":1,"mn":"ADBE Vector Group","hd":false}],"ip":0,"op":125,"st":0,"bm":0},{"ddd":0,"ind":11,"ty":4,"nm":"Circkle_2","sr":1,"ks":{"o":{"a":0,"k":90,"ix":11},"r":{"a":0,"k":0,"ix":10},"p":{"a":0,"k":[300,300,0],"ix":2},"a":{"a":0,"k":[0,0,0],"ix":1},"s":{"a":0,"k":[100,100,100],"ix":6}},"ao":0,"shapes":[{"ty":"gr","it":[{"ind":0,"ty":"sh","ix":1,"ks":{"a":0,"k":{"i":[[0,-90.175],[90.175,0],[0,90.175],[-90.175,0]],"o":[[0,90.175],[-90.175,0],[0,-90.175],[90.175,0]],"v":[[163.275,0],[0,163.275],[-163.275,0],[0,-163.275]],"c":true},"ix":2},"nm":"Path 1","mn":"ADBE Vector Shape - Group","hd":false},{"ty":"gs","o":{"a":0,"k":100,"ix":9},"w":{"a":0,"k":0.5,"ix":10},"g":{"p":3,"k":{"a":0,"k":[0,1,0.498,0.047,0.5,0.992,0.263,0.245,1,0.984,0.027,0.443],"ix":8}},"s":{"a":0,"k":[-153,55],"ix":4},"e":{"a":0,"k":[154.317,-56.854],"ix":5},"t":1,"lc":1,"lj":1,"ml":10,"ml2":{"a":0,"k":10,"ix":13},"bm":0,"nm":"Gradient Stroke 1","mn":"ADBE Vector Graphic - G-Stroke","hd":false},{"ty":"tr","p":{"a":0,"k":[0,0],"ix":2},"a":{"a":0,"k":[0,0],"ix":1},"s":{"a":0,"k":[100,100],"ix":3},"r":{"a":0,"k":0,"ix":6},"o":{"a":0,"k":100,"ix":7},"sk":{"a":0,"k":0,"ix":4},"sa":{"a":0,"k":0,"ix":5},"nm":"Transform"}],"nm":"Group 1","np":2,"cix":2,"bm":0,"ix":1,"mn":"ADBE Vector Group","hd":false}],"ip":0,"op":125,"st":0,"bm":0},{"ddd":0,"ind":12,"ty":4,"nm":"Circkle_1","sr":1,"ks":{"o":{"a":0,"k":100,"ix":11},"r":{"a":0,"k":0,"ix":10},"p":{"a":0,"k":[301.292,301.153,0],"ix":2},"a":{"a":0,"k":[0,0,0],"ix":1},"s":{"a":0,"k":[100,100,100],"ix":6}},"ao":0,"shapes":[{"ty":"gr","it":[{"d":1,"ty":"el","s":{"a":0,"k":[294.967,294.967],"ix":2},"p":{"a":0,"k":[0,0],"ix":3},"nm":"Ellipse Path 1","mn":"ADBE Vector Shape - Ellipse","hd":false},{"ty":"gs","o":{"a":0,"k":100,"ix":9},"w":{"a":0,"k":0.5,"ix":10},"g":{"p":3,"k":{"a":0,"k":[0,1,0.498,0.047,0.5,0.992,0.263,0.245,1,0.984,0.027,0.443],"ix":8}},"s":{"a":0,"k":[-137,51],"ix":4},"e":{"a":0,"k":[140.63,-50.049],"ix":5},"t":1,"lc":1,"lj":1,"ml":10,"ml2":{"a":0,"k":10,"ix":13},"bm":0,"nm":"Gradient Stroke 1","mn":"ADBE Vector Graphic - G-Stroke","hd":false},{"ty":"tr","p":{"a":0,"k":[0,0],"ix":2},"a":{"a":0,"k":[0,0],"ix":1},"s":{"a":0,"k":[100,100],"ix":3},"r":{"a":0,"k":0,"ix":6},"o":{"a":0,"k":100,"ix":7},"sk":{"a":0,"k":0,"ix":4},"sa":{"a":0,"k":0,"ix":5},"nm":"Transform"}],"nm":"Group 1","np":2,"cix":2,"bm":0,"ix":1,"mn":"ADBE Vector Group","hd":false}],"ip":0,"op":125,"st":0,"bm":0},{"ddd":0,"ind":13,"ty":4,"nm":"Circkle_18","sr":1,"ks":{"o":{"a":1,"k":[{"i":{"x":[0.833],"y":[0.833]},"o":{"x":[0.167],"y":[0.167]},"t":15,"s":[20]},{"t":121,"s":[0]}],"ix":11},"r":{"a":0,"k":0,"ix":10},"p":{"a":0,"k":[300,300,0],"ix":2},"a":{"a":0,"k":[0,0,0],"ix":1},"s":{"a":1,"k":[{"i":{"x":[0,0,0.667],"y":[1,1,1]},"o":{"x":[0.333,0.333,0.333],"y":[0,0,0]},"t":15,"s":[0,0,100]},{"t":121,"s":[100,100,100]}],"ix":6}},"ao":0,"shapes":[{"ty":"gr","it":[{"ind":0,"ty":"sh","ix":1,"ks":{"a":0,"k":{"i":[[0,-155.858],[155.858,0],[0,155.858],[-155.858,0]],"o":[[0,155.858],[-155.858,0],[0,-155.858],[155.858,0]],"v":[[282.206,0],[0,282.206],[-282.206,0],[0,-282.206]],"c":true},"ix":2},"nm":"Path 1","mn":"ADBE Vector Shape - Group","hd":false},{"ty":"st","c":{"a":0,"k":[0.458823529412,0.458823529412,0.458823529412,1],"ix":3},"o":{"a":0,"k":100,"ix":4},"w":{"a":0,"k":1,"ix":5},"lc":1,"lj":1,"ml":4,"bm":0,"nm":"Stroke 1","mn":"ADBE Vector Graphic - Stroke","hd":false},{"ty":"fl","c":{"a":0,"k":[0,0,0,1],"ix":4},"o":{"a":0,"k":15,"ix":5},"r":1,"bm":0,"nm":"Fill 1","mn":"ADBE Vector Graphic - Fill","hd":false},{"ty":"tr","p":{"a":0,"k":[0,0],"ix":2},"a":{"a":0,"k":[0,0],"ix":1},"s":{"a":0,"k":[100,100],"ix":3},"r":{"a":0,"k":0,"ix":6},"o":{"a":0,"k":100,"ix":7},"sk":{"a":0,"k":0,"ix":4},"sa":{"a":0,"k":0,"ix":5},"nm":"Transform"}],"nm":"Group 1","np":3,"cix":2,"bm":0,"ix":1,"mn":"ADBE Vector Group","hd":false}],"ip":0,"op":125,"st":0,"bm":0},{"ddd":0,"ind":14,"ty":4,"nm":"Circkle_17","sr":1,"ks":{"o":{"a":1,"k":[{"i":{"x":[0.833],"y":[0.833]},"o":{"x":[0.167],"y":[0.167]},"t":20.625,"s":[30]},{"t":121,"s":[0]}],"ix":11},"r":{"a":0,"k":0,"ix":10},"p":{"a":0,"k":[300,300,0],"ix":2},"a":{"a":0,"k":[0,0,0],"ix":1},"s":{"a":1,"k":[{"i":{"x":[0,0,0.667],"y":[1,1,1]},"o":{"x":[0.333,0.333,0.333],"y":[0,0,0]},"t":20.625,"s":[0,0,100]},{"t":121,"s":[100,100,100]}],"ix":6}},"ao":0,"shapes":[{"ty":"gr","it":[{"ind":0,"ty":"sh","ix":1,"ks":{"a":0,"k":{"i":[[0,-147.72],[147.72,0],[0,147.72],[-147.72,0]],"o":[[0,147.72],[-147.72,0],[0,-147.72],[147.72,0]],"v":[[267.47,0],[0,267.47],[-267.47,0],[0,-267.47]],"c":true},"ix":2},"nm":"Path 1","mn":"ADBE Vector Shape - Group","hd":false},{"ty":"st","c":{"a":0,"k":[0.458823529412,0.458823529412,0.458823529412,1],"ix":3},"o":{"a":0,"k":100,"ix":4},"w":{"a":0,"k":1,"ix":5},"lc":1,"lj":1,"ml":4,"bm":0,"nm":"Stroke 1","mn":"ADBE Vector Graphic - Stroke","hd":false},{"ty":"tr","p":{"a":0,"k":[0,0],"ix":2},"a":{"a":0,"k":[0,0],"ix":1},"s":{"a":0,"k":[100,100],"ix":3},"r":{"a":0,"k":0,"ix":6},"o":{"a":0,"k":100,"ix":7},"sk":{"a":0,"k":0,"ix":4},"sa":{"a":0,"k":0,"ix":5},"nm":"Transform"}],"nm":"Group 1","np":2,"cix":2,"bm":0,"ix":1,"mn":"ADBE Vector Group","hd":false}],"ip":0,"op":125,"st":0,"bm":0},{"ddd":0,"ind":15,"ty":4,"nm":"Circkle_16","sr":1,"ks":{"o":{"a":1,"k":[{"i":{"x":[0.833],"y":[0.833]},"o":{"x":[0.167],"y":[0.167]},"t":26.25,"s":[40]},{"t":121,"s":[0]}],"ix":11},"r":{"a":0,"k":0,"ix":10},"p":{"a":0,"k":[300,300,0],"ix":2},"a":{"a":0,"k":[0,0,0],"ix":1},"s":{"a":1,"k":[{"i":{"x":[0,0,0.667],"y":[1,1,1]},"o":{"x":[0.333,0.333,0.333],"y":[0,0,0]},"t":26.25,"s":[0,0,100]},{"t":121,"s":[100,100,100]}],"ix":6}},"ao":0,"shapes":[{"ty":"gr","it":[{"ind":0,"ty":"sh","ix":1,"ks":{"a":0,"k":{"i":[[0,-139.076],[139.076,0],[0,139.076],[-139.076,0]],"o":[[0,139.076],[-139.076,0],[0,-139.076],[139.076,0]],"v":[[251.819,0],[0,251.819],[-251.819,0],[0,-251.819]],"c":true},"ix":2},"nm":"Path 1","mn":"ADBE Vector Shape - Group","hd":false},{"ty":"st","c":{"a":0,"k":[0.458823529412,0.458823529412,0.458823529412,1],"ix":3},"o":{"a":0,"k":100,"ix":4},"w":{"a":0,"k":1,"ix":5},"lc":1,"lj":1,"ml":4,"bm":0,"nm":"Stroke 1","mn":"ADBE Vector Graphic - Stroke","hd":false},{"ty":"tr","p":{"a":0,"k":[0,0],"ix":2},"a":{"a":0,"k":[0,0],"ix":1},"s":{"a":0,"k":[100,100],"ix":3},"r":{"a":0,"k":0,"ix":6},"o":{"a":0,"k":100,"ix":7},"sk":{"a":0,"k":0,"ix":4},"sa":{"a":0,"k":0,"ix":5},"nm":"Transform"}],"nm":"Group 1","np":2,"cix":2,"bm":0,"ix":1,"mn":"ADBE Vector Group","hd":false}],"ip":0,"op":125,"st":0,"bm":0},{"ddd":0,"ind":16,"ty":4,"nm":"Circkle_15","sr":1,"ks":{"o":{"a":1,"k":[{"i":{"x":[0.833],"y":[0.833]},"o":{"x":[0.167],"y":[0.167]},"t":31.875,"s":[50]},{"t":121,"s":[0]}],"ix":11},"r":{"a":0,"k":0,"ix":10},"p":{"a":0,"k":[300,300,0],"ix":2},"a":{"a":0,"k":[0,0,0],"ix":1},"s":{"a":1,"k":[{"i":{"x":[0,0,0.667],"y":[1,1,1]},"o":{"x":[0.333,0.333,0.333],"y":[0,0,0]},"t":31.875,"s":[0,0,100]},{"t":121,"s":[100,100,100]}],"ix":6}},"ao":0,"shapes":[{"ty":"gr","it":[{"d":1,"ty":"el","s":{"a":0,"k":[464.729,464.729],"ix":2},"p":{"a":0,"k":[0,0],"ix":3},"nm":"Ellipse Path 1","mn":"ADBE Vector Shape - Ellipse","hd":false},{"ty":"st","c":{"a":0,"k":[0.458823529412,0.458823529412,0.458823529412,1],"ix":3},"o":{"a":0,"k":100,"ix":4},"w":{"a":0,"k":1,"ix":5},"lc":1,"lj":1,"ml":4,"bm":0,"nm":"Stroke 1","mn":"ADBE Vector Graphic - Stroke","hd":false},{"ty":"tr","p":{"a":0,"k":[0,0],"ix":2},"a":{"a":0,"k":[0,0],"ix":1},"s":{"a":0,"k":[100,100],"ix":3},"r":{"a":0,"k":0,"ix":6},"o":{"a":0,"k":100,"ix":7},"sk":{"a":0,"k":0,"ix":4},"sa":{"a":0,"k":0,"ix":5},"nm":"Transform"}],"nm":"Group 1","np":2,"cix":2,"bm":0,"ix":1,"mn":"ADBE Vector Group","hd":false}],"ip":0,"op":125,"st":0,"bm":0},{"ddd":0,"ind":17,"ty":4,"nm":"Circkle_14","sr":1,"ks":{"o":{"a":1,"k":[{"i":{"x":[0.833],"y":[0.833]},"o":{"x":[0.167],"y":[0.167]},"t":37.5,"s":[60]},{"t":121,"s":[0]}],"ix":11},"r":{"a":0,"k":0,"ix":10},"p":{"a":0,"k":[300,300,0],"ix":2},"a":{"a":0,"k":[0,0,0],"ix":1},"s":{"a":1,"k":[{"i":{"x":[0,0,0.667],"y":[1,1,1]},"o":{"x":[0.333,0.333,0.333],"y":[0,0,0]},"t":37.5,"s":[0,0,100]},{"t":121,"s":[100,100,100]}],"ix":6}},"ao":0,"shapes":[{"ty":"gr","it":[{"d":1,"ty":"el","s":{"a":0,"k":[429.527,429.527],"ix":2},"p":{"a":0,"k":[0,0],"ix":3},"nm":"Ellipse Path 1","mn":"ADBE Vector Shape - Ellipse","hd":false},{"ty":"st","c":{"a":0,"k":[0.458823529412,0.458823529412,0.458823529412,1],"ix":3},"o":{"a":0,"k":100,"ix":4},"w":{"a":0,"k":1,"ix":5},"lc":1,"lj":1,"ml":4,"bm":0,"nm":"Stroke 1","mn":"ADBE Vector Graphic - Stroke","hd":false},{"ty":"tr","p":{"a":0,"k":[0,0],"ix":2},"a":{"a":0,"k":[0,0],"ix":1},"s":{"a":0,"k":[100,100],"ix":3},"r":{"a":0,"k":0,"ix":6},"o":{"a":0,"k":100,"ix":7},"sk":{"a":0,"k":0,"ix":4},"sa":{"a":0,"k":0,"ix":5},"nm":"Transform"}],"nm":"Group 1","np":2,"cix":2,"bm":0,"ix":1,"mn":"ADBE Vector Group","hd":false}],"ip":0,"op":125,"st":0,"bm":0},{"ddd":0,"ind":18,"ty":4,"nm":"Circkle_13","sr":1,"ks":{"o":{"a":1,"k":[{"i":{"x":[0.833],"y":[0.833]},"o":{"x":[0.167],"y":[0.167]},"t":43.125,"s":[70]},{"t":121,"s":[0]}],"ix":11},"r":{"a":0,"k":0,"ix":10},"p":{"a":0,"k":[300,300,0],"ix":2},"a":{"a":0,"k":[0,0,0],"ix":1},"s":{"a":1,"k":[{"i":{"x":[0,0,0.667],"y":[1,1,1]},"o":{"x":[0.333,0.333,0.333],"y":[0,0,0]},"t":43.125,"s":[0,0,100]},{"t":121,"s":[100,100,100]}],"ix":6}},"ao":0,"shapes":[{"ty":"gr","it":[{"ind":0,"ty":"sh","ix":1,"ks":{"a":0,"k":{"i":[[0,-108.43],[108.43,0],[0,108.43],[-108.43,0]],"o":[[0,108.43],[-108.43,0],[0,-108.43],[108.43,0]],"v":[[196.33,0],[0,196.33],[-196.33,0],[0,-196.33]],"c":true},"ix":2},"nm":"Path 1","mn":"ADBE Vector Shape - Group","hd":false},{"ty":"st","c":{"a":0,"k":[0.458823529412,0.458823529412,0.458823529412,1],"ix":3},"o":{"a":0,"k":100,"ix":4},"w":{"a":0,"k":1,"ix":5},"lc":1,"lj":1,"ml":4,"bm":0,"nm":"Stroke 1","mn":"ADBE Vector Graphic - Stroke","hd":false},{"ty":"tr","p":{"a":0,"k":[0,0],"ix":2},"a":{"a":0,"k":[0,0],"ix":1},"s":{"a":0,"k":[100,100],"ix":3},"r":{"a":0,"k":0,"ix":6},"o":{"a":0,"k":100,"ix":7},"sk":{"a":0,"k":0,"ix":4},"sa":{"a":0,"k":0,"ix":5},"nm":"Transform"}],"nm":"Group 1","np":2,"cix":2,"bm":0,"ix":1,"mn":"ADBE Vector Group","hd":false}],"ip":0,"op":125,"st":0,"bm":0},{"ddd":0,"ind":19,"ty":4,"nm":"Circkle_12","sr":1,"ks":{"o":{"a":1,"k":[{"i":{"x":[0.833],"y":[0.833]},"o":{"x":[0.167],"y":[0.167]},"t":48.75,"s":[80]},{"t":121,"s":[0]}],"ix":11},"r":{"a":0,"k":0,"ix":10},"p":{"a":0,"k":[300,300,0],"ix":2},"a":{"a":0,"k":[0,0,0],"ix":1},"s":{"a":1,"k":[{"i":{"x":[0,0,0.667],"y":[1,1,1]},"o":{"x":[0.333,0.333,0.333],"y":[0,0,0]},"t":48.75,"s":[0,0,100]},{"t":121,"s":[100,100,100]}],"ix":6}},"ao":0,"shapes":[{"ty":"gr","it":[{"d":1,"ty":"el","s":{"a":0,"k":[361.075,361.075],"ix":2},"p":{"a":0,"k":[0,0],"ix":3},"nm":"Ellipse Path 1","mn":"ADBE Vector Shape - Ellipse","hd":false},{"ty":"st","c":{"a":0,"k":[0.458823529412,0.458823529412,0.458823529412,1],"ix":3},"o":{"a":0,"k":100,"ix":4},"w":{"a":0,"k":1,"ix":5},"lc":1,"lj":1,"ml":4,"bm":0,"nm":"Stroke 1","mn":"ADBE Vector Graphic - Stroke","hd":false},{"ty":"tr","p":{"a":0,"k":[0,0],"ix":2},"a":{"a":0,"k":[0,0],"ix":1},"s":{"a":0,"k":[100,100],"ix":3},"r":{"a":0,"k":0,"ix":6},"o":{"a":0,"k":100,"ix":7},"sk":{"a":0,"k":0,"ix":4},"sa":{"a":0,"k":0,"ix":5},"nm":"Transform"}],"nm":"Group 1","np":2,"cix":2,"bm":0,"ix":1,"mn":"ADBE Vector Group","hd":false}],"ip":0,"op":125,"st":0,"bm":0},{"ddd":0,"ind":20,"ty":4,"nm":"Circkle_11","sr":1,"ks":{"o":{"a":1,"k":[{"i":{"x":[0.833],"y":[0.833]},"o":{"x":[0.167],"y":[0.167]},"t":54.375,"s":[90]},{"t":121,"s":[0]}],"ix":11},"r":{"a":0,"k":0,"ix":10},"p":{"a":0,"k":[300,300,0],"ix":2},"a":{"a":0,"k":[0,0,0],"ix":1},"s":{"a":1,"k":[{"i":{"x":[0,0,0.667],"y":[1,1,1]},"o":{"x":[0.333,0.333,0.333],"y":[0,0,0]},"t":54.375,"s":[0,0,100]},{"t":121,"s":[100,100,100]}],"ix":6}},"ao":0,"shapes":[{"ty":"gr","it":[{"ind":0,"ty":"sh","ix":1,"ks":{"a":0,"k":{"i":[[0,-90.175],[90.175,0],[0,90.175],[-90.175,0]],"o":[[0,90.175],[-90.175,0],[0,-90.175],[90.175,0]],"v":[[163.275,0],[0,163.275],[-163.275,0],[0,-163.275]],"c":true},"ix":2},"nm":"Path 1","mn":"ADBE Vector Shape - Group","hd":false},{"ty":"st","c":{"a":0,"k":[0.458823529412,0.458823529412,0.458823529412,1],"ix":3},"o":{"a":0,"k":100,"ix":4},"w":{"a":0,"k":1,"ix":5},"lc":1,"lj":1,"ml":4,"bm":0,"nm":"Stroke 1","mn":"ADBE Vector Graphic - Stroke","hd":false},{"ty":"tr","p":{"a":0,"k":[0,0],"ix":2},"a":{"a":0,"k":[0,0],"ix":1},"s":{"a":0,"k":[100,100],"ix":3},"r":{"a":0,"k":0,"ix":6},"o":{"a":0,"k":100,"ix":7},"sk":{"a":0,"k":0,"ix":4},"sa":{"a":0,"k":0,"ix":5},"nm":"Transform"}],"nm":"Group 1","np":2,"cix":2,"bm":0,"ix":1,"mn":"ADBE Vector Group","hd":false}],"ip":0,"op":125,"st":0,"bm":0},{"ddd":0,"ind":21,"ty":4,"nm":"Circkle_10","sr":1,"ks":{"o":{"a":1,"k":[{"i":{"x":[0.833],"y":[0.833]},"o":{"x":[0.167],"y":[0.167]},"t":60,"s":[100]},{"t":121,"s":[0]}],"ix":11},"r":{"a":0,"k":0,"ix":10},"p":{"a":0,"k":[301.292,301.153,0],"ix":2},"a":{"a":0,"k":[0,0,0],"ix":1},"s":{"a":1,"k":[{"i":{"x":[0,0,0.667],"y":[1,1,1]},"o":{"x":[0.333,0.333,0.333],"y":[0,0,0]},"t":60,"s":[0,0,100]},{"t":121,"s":[100,100,100]}],"ix":6}},"ao":0,"shapes":[{"ty":"gr","it":[{"d":1,"ty":"el","s":{"a":0,"k":[294.967,294.967],"ix":2},"p":{"a":0,"k":[0,0],"ix":3},"nm":"Ellipse Path 1","mn":"ADBE Vector Shape - Ellipse","hd":false},{"ty":"st","c":{"a":0,"k":[0.458823529412,0.458823529412,0.458823529412,1],"ix":3},"o":{"a":0,"k":100,"ix":4},"w":{"a":0,"k":1,"ix":5},"lc":1,"lj":1,"ml":4,"bm":0,"nm":"Stroke 1","mn":"ADBE Vector Graphic - Stroke","hd":false},{"ty":"tr","p":{"a":0,"k":[0,0],"ix":2},"a":{"a":0,"k":[0,0],"ix":1},"s":{"a":0,"k":[100,100],"ix":3},"r":{"a":0,"k":0,"ix":6},"o":{"a":0,"k":100,"ix":7},"sk":{"a":0,"k":0,"ix":4},"sa":{"a":0,"k":0,"ix":5},"nm":"Transform"}],"nm":"Group 1","np":2,"cix":2,"bm":0,"ix":1,"mn":"ADBE Vector Group","hd":false}],"ip":0,"op":125,"st":0,"bm":0}],"markers":[]}